[
  {
    "Id": 1,
    "Name": "Koehler's Rockcress",
    "Content": "Bypass Right Ureter to Colon, Open Approach",
    "Type": 1,
    "StartTime": "2023-04-14T11:30:52Z",
    "EndTime": "2023-05-10T00:00:00Z",
    "TrainingClassId": 4,
    "SyllabusId": 1
  },
  {
    "Id": 2,
    "Name": "Physciella",
    "Content": "Beam Radiation of Peripheral Nerve using Photons >10 MeV",
    "Type": 2,
    "StartTime": "2023-04-10T19:57:38Z",
    "EndTime": "2023-05-10T00:00:00Z",
    "TrainingClassId": 4,
    "SyllabusId": 1
  },
  {
    "Id": 3,
    "Name": "Santa Clara Thorn-mint",
    "Content": "Revision of Infusion Device in Right Lower Extremity, Open Approach",
    "Type": 3,
    "StartTime": "2023-04-14T10:58:57Z",
    "EndTime": "2023-05-10T00:00:00Z",
    "TrainingClassId": 4,
    "SyllabusId": 1
  },
  {
    "Id": 4,
    "Name": "Creeping Charlie",
    "Content": "Reposition Right Toe Phalangeal Joint with Internal Fixation Device, Percutaneous Approach",
    "Type": 0,
    "StartTime": "2023-04-10T21:48:52Z",
    "EndTime": "2023-05-10T00:00:00Z",
    "TrainingClassId": 4,
    "SyllabusId": 1
  },
  {
    "Id": 5,
    "Name": "Florida Keys Indian Mallow",
    "Content": "Coordination/Dexterity Treatment of Integumentary System - Lower Back / Lower Extremity using Orthosis",
    "Type": 3,
    "StartTime": "2023-04-11T15:47:44Z",
    "EndTime": "2023-05-10T00:00:00Z",
    "TrainingClassId": 4,
    "SyllabusId": 1
  },
  {
    "Id": 6,
    "Name": "Intermediate Needle And Thread",
    "Content": "Dilation of Right External Iliac Artery, Bifurcation, with Four or More Intraluminal Devices, Percutaneous Endoscopic Approach",
    "Type": 1,
    "StartTime": "2023-04-14T17:24:26Z",
    "EndTime": "2023-05-10T00:00:00Z",
    "TrainingClassId": 4,
    "SyllabusId": 1
  },
  {
    "Id": 7,
    "Name": "Coenogonium Lichen",
    "Content": "Drainage of Right Upper Extremity Bursa and Ligament with Drainage Device, Percutaneous Endoscopic Approach",
    "Type": 2,
    "StartTime": "2023-04-11T06:51:24Z",
    "EndTime": "2023-05-10T00:00:00Z",
    "TrainingClassId": 4,
    "SyllabusId": 1
  },
  {
    "Id": 8,
    "Name": "Windmill Grass",
    "Content": "Revision of Internal Fixation Device in Right Carpal Joint, Percutaneous Approach",
    "Type": 1,
    "StartTime": "2023-04-14T19:28:55Z",
    "EndTime": "2023-05-10T00:00:00Z",
    "TrainingClassId": 4,
    "SyllabusId": 1
  },
  {
    "Id": 9,
    "Name": "Batoko Plum",
    "Content": "Removal of Internal Fixation Device from Left Humeral Shaft, Open Approach",
    "Type": 1,
    "StartTime": "2023-04-13T23:34:19Z",
    "EndTime": "2023-05-10T00:00:00Z",
    "TrainingClassId": 4,
    "SyllabusId": 1
  },
  {
    "Id": 10,
    "Name": "Grove Hawthorn",
    "Content": "Bypass Coronary Artery, Two Arteries from Aorta with Zooplastic Tissue, Open Approach",
    "Type": 3,
    "StartTime": "2023-04-10T21:03:29Z",
    "EndTime": "2023-05-10T00:00:00Z",
    "TrainingClassId": 4,
    "SyllabusId": 1
  }
]