[
  {
    "Id": 6,
    "UserName": "gkitley5",
    "Password": "YKuiCBqHNZU",
    "FullName": "Georges Kitley",
    "Email": "gkitley5@walmart.com",
    "DateOfBorth": "1995-03-25T09:25:33Z",
    "PhoneNumber": "9945804139",
    "Level": "Century",
    "Gender": 0,
    "Status": 3,
    "Role": 4,
    "TrainingClassId": 4
  },
  {
    "Id": 7,
    "UserName": "asupple6",
    "Password": "4CoeQvR",
    "FullName": "Arlinda Supple",
    "Email": "asupple6@eepurl.com",
    "DateOfBorth": "1991-01-23T04:09:15Z",
    "PhoneNumber": "7375167719",
    "Level": "TrailBlazer",
    "Gender": 0,
    "Status": 3,
    "Role": 4,
    "TrainingClassId": 4
  },
  {
    "Id": 8,
    "UserName": "pcanto7",
    "Password": "lFoCGG",
    "FullName": "Prudence Canto",
    "Email": "pcanto7@irs.gov",
    "DateOfBorth": "1993-01-25T01:25:46Z",
    "PhoneNumber": "2195699692",
    "Level": "Sienna",
    "Gender": 0,
    "Status": 3,
    "Role": 4,
    "TrainingClassId": 4
  },
  {
    "Id": 9,
    "UserName": "gfugere8",
    "Password": "phNbllvMJtp",
    "FullName": "Giavani Fugere",
    "Email": "gfugere8@cbc.ca",
    "DateOfBorth": "1994-04-21T03:11:07Z",
    "PhoneNumber": "7301345872",
    "Level": "Corvette",
    "Gender": 0,
    "Status": 3,
    "Role": 4,
    "TrainingClassId": 4
  },
  {
    "Id": 10,
    "UserName": "jfone9",
    "Password": "6UbhxiJ5MuqQ",
    "FullName": "Jasen Fone",
    "Email": "jfone9@blog.com",
    "DateOfBorth": "1993-12-24T03:58:07Z",
    "PhoneNumber": "1643273348",
    "Level": "Soul",
    "Gender": 0,
    "Status": 3,
    "Role": 4,
    "TrainingClassId": 4
  },
  {
    "Id": 11,
    "UserName": "ofacera",
    "Password": "AKXq1GK",
    "FullName": "Othilia Facer",
    "Email": "ofacera@yellowbook.com",
    "DateOfBorth": "1992-02-28T14:16:07Z",
    "PhoneNumber": "3497504380",
    "Level": "3500 Club Coupe",
    "Gender": 1,
    "Status": 3,
    "Role": 4,
    "TrainingClassId": 4
  },
  {
    "Id": 12,
    "UserName": "lconnorsb",
    "Password": "fF49lx",
    "FullName": "Loralee Connors",
    "Email": "lconnorsb@cbslocal.com",
    "DateOfBorth": "1997-12-16T04:31:29Z",
    "PhoneNumber": "4891190366",
    "Level": "Galant",
    "Gender": 1,
    "Status": 3,
    "Role": 4,
    "TrainingClassId": 4
  },
  {
    "Id": 13,
    "UserName": "cohearnc",
    "Password": "QSg7QuJnG",
    "FullName": "Creighton O'Hearn",
    "Email": "cohearnc@ft.com",
    "DateOfBorth": "1995-06-10T08:48:42Z",
    "PhoneNumber": "6795687417",
    "Level": "911",
    "Gender": 1,
    "Status": 3,
    "Role": 4,
    "TrainingClassId": 4
  },
  {
    "Id": 14,
    "UserName": "pmessittd",
    "Password": "ktFp8NnlOKb",
    "FullName": "Padraic Messitt",
    "Email": "pmessittd@amazonaws.com",
    "DateOfBorth": "1995-05-27T08:03:25Z",
    "PhoneNumber": "5959334108",
    "Level": "Cooper Clubman",
    "Gender": 1,
    "Status": 3,
    "Role": 4,
    "TrainingClassId": 4
  },
  {
    "Id": 15,
    "UserName": "lmuffine",
    "Password": "BFibYI4e4Xu",
    "FullName": "Lesly Muffin",
    "Email": "lmuffine@whitehouse.gov",
    "DateOfBorth": "1995-02-08T03:29:04Z",
    "PhoneNumber": "8541984843",
    "Level": "CX-9",
    "Gender": 1,
    "Status": 3,
    "Role": 4,
    "TrainingClassId": 4
  }
]